{
  "config": {
    "step": {
      "user": {
        "title": "Jet2 - Add a booking",
        "data": {
          "booking_reference": "Booking Reference",
          "calendars": "Add events to calendar(s)",
          "date_of_birth": "Lead Passenger Date of Birth (DD/MM/YYYY)",
          "surname": "Lead Passenger Surname"
        }
      }
    },
    "error": {
      "booking_exists": "This booking already exists",
      "cannot_connect": "[%key:common::config_flow::error::cannot_connect%]",
      "invalid_auth": "[%key:common::config_flow::error::invalid_auth%]",
      "invalid_date_format": "Date must be in DD/MM/YYYY format",
      "no_calendar_selected": "You must select at least one calendar",
      "unknown": "[%key:common::config_flow::error::unknown%]"
    },
    "abort": {
      "already_configured": "Integration is already configured",
      "booking_removed": "Booking removed"
    }
  },
  "services": {
    "add_booking": {
      "name": "Add Booking",
      "description": "Add a Jet2 booking",
      "fields": {
        "booking_reference": {
          "name": "Booking Reference",
          "description": "You'll find your booking reference in your booking confirmation email. e.g. 12345678/X12H"
        },
        "create_calendar": {
          "name": "Create Calendar",
          "description": "Create a new calendar specifically for this booking"
        },
        "date_of_birth": {
          "name": "Date of Birth",
          "description": "Lead Passenger Date of Birth DD/MM/YYYY"
        },
        "surname": {
          "name": "Surname",
          "description": "Lead Passenger Surname"
        }
      }
    },
    "remove_booking": {
      "name": "Remove Booking",
      "description": "Remove a Jet2 booking",
      "fields": {
        "booking_reference": {
          "name": "Booking Reference",
          "description": "You'll find your booking reference in your booking confirmation email. e.g. 12345678/X12H"
        }
      }
    }
  }
}
